dify_client/__init__.py
dify_client/async_client.py
dify_client/client.py
dify_python_sdk-0.1.15.dist-info/METADATA
dify_python_sdk-0.1.15.dist-info/WHEEL
dify_python_sdk-0.1.15.dist-info/licenses/LICENSE
dify_python_sdk-0.1.15.dist-info/licenses/NOTICE
dify_python_sdk-0.1.15.dist-info/RECORD
