Metadata-Version: 2.4
Name: dify-python-sdk
Version: 0.1.15
Summary: A package for interacting with the Dify Service-API (based on dify-client)
Project-URL: Homepage, https://github.com/lyzno1/dify-python-sdk
Author-email: yuanyouhui <yuanyouhuilyz@gmail.com>
License: MIT
License-File: LICENSE
License-File: NOTICE
Keywords: ai,dify,language-processing,nlp
Classifier: License :: OSI Approved :: MIT License
Classifier: Operating System :: OS Independent
Classifier: Programming Language :: Python :: 3
Requires-Python: >=3.10
Requires-Dist: aiofiles>=23.0.0
Requires-Dist: httpx>=0.27.0
Provides-Extra: dev
Requires-Dist: pytest-asyncio>=0.21.0; extra == 'dev'
Requires-Dist: pytest>=7.0.0; extra == 'dev'
